weibo_text_analysis/__init__.py
weibo_text_analysis/sentiment_utils.py
weibo_text_analysis/text_utils.py
weibo_text_analysis/time_utils.py
weibo_text_analysis/__pycache__/__init__.cpython-39.pyc
weibo_text_analysis/__pycache__/text_utils.cpython-39.pyc
weibo_text_analysis-0.0.1a0.dist-info/LICENSE
weibo_text_analysis-0.0.1a0.dist-info/METADATA
weibo_text_analysis-0.0.1a0.dist-info/WHEEL
weibo_text_analysis-0.0.1a0.dist-info/top_level.txt
weibo_text_analysis-0.0.1a0.dist-info/RECORD
